setup.cfg
setup.py
mETL.egg-info/PKG-INFO
mETL.egg-info/SOURCES.txt
mETL.egg-info/dependency_links.txt
mETL.egg-info/entry_points.txt
mETL.egg-info/not-zip-safe
mETL.egg-info/requires.txt
mETL.egg-info/top_level.txt
metl/__init__.py
metl/base.py
metl/config.py
metl/configparser.py
metl/exception.py
metl/field.py
metl/fieldmap.py
metl/fieldset.py
metl/guess.py
metl/guessfieldset.py
metl/guessmanager.py
metl/manager.py
metl/manipulation.py
metl/migration.py
metl/reader.py
metl/script.py
metl/tarrdispatcher.py
metl/transfer.py
metl/utils.py
metl/writer.py
metl/aggregator/__init__.py
metl/aggregator/avgaggregator.py
metl/aggregator/base.py
metl/aggregator/countaggregator.py
metl/aggregator/sumaggregator.py
metl/condition/__init__.py
metl/condition/base.py
metl/condition/isbetweencondition.py
metl/condition/isemptycondition.py
metl/condition/isequalcondition.py
metl/condition/isgreaterandequalcondition.py
metl/condition/isgreatercondition.py
metl/condition/isincondition.py
metl/condition/isinsourcecondition.py
metl/condition/islessandequalcondition.py
metl/condition/islesscondition.py
metl/condition/ismatchbyregexpcondition.py
metl/database/__init__.py
metl/database/alchemydatabase.py
metl/database/basedatabase.py
metl/database/postgresqldatabase.py
metl/expand/__init__.py
metl/expand/appendallexpand.py
metl/expand/appendbysourceexpand.py
metl/expand/appendexpand.py
metl/expand/base.py
metl/expand/baseexpanderexpand.py
metl/expand/fieldexpand.py
metl/expand/listexpanderexpand.py
metl/expand/meltexpand.py
metl/fieldtype/__init__.py
metl/fieldtype/base.py
metl/fieldtype/bigintegerfieldtype.py
metl/fieldtype/booleanfieldtype.py
metl/fieldtype/complexfieldtype.py
metl/fieldtype/datefieldtype.py
metl/fieldtype/datetimefieldtype.py
metl/fieldtype/floatfieldtype.py
metl/fieldtype/integerfieldtype.py
metl/fieldtype/listfieldtype.py
metl/fieldtype/picklefieldtype.py
metl/fieldtype/stringfieldtype.py
metl/fieldtype/textfieldtype.py
metl/fieldtype/unknownfieldtype.py
metl/filter/__init__.py
metl/filter/base.py
metl/filter/dropbyconditionfilter.py
metl/filter/dropbysourcefilter.py
metl/filter/dropfieldfilter.py
metl/filter/keepbyconditionfilter.py
metl/modifier/__init__.py
