Metadata-Version: 1.0
Name: mETL
Version: 1.0.6
Summary: ETL processes with easy config
Home-page: UNKNOWN
Author: Bence Faludi
Author-email: b.faludi@mito.hu
License: GPL
Platform: UNKNOWN
